examples/OracleRule.py
examples/__init__.py
examples/nodeList.py
examples/repBackupList.py
info2soft/__init__.py
info2soft/compat.py
info2soft/config.py
info2soft/fileWriter.py
info2soft/https.py
info2soft/ContainerCls/__init__.py
info2soft/ContainerCls/v20240819/ContainerCls.py
info2soft/ContainerCls/v20240819/__init__.py
info2soft/ContainerCls/v20250123/ContainerCls.py
info2soft/ContainerCls/v20250123/__init__.py
info2soft/ContainerCls/v20250630/ContainerCls.py
info2soft/ContainerCls/v20250630/__init__.py
info2soft/TapeCopy/__init__.py
info2soft/TapeCopy/v20240819/TapeCopy.py
info2soft/TapeCopy/v20240819/__init__.py
info2soft/TapeCopy/v20250123/TapeCopy.py
info2soft/TapeCopy/v20250123/__init__.py
info2soft/TapeCopy/v20250630/TapeCopy.py
info2soft/TapeCopy/v20250630/__init__.py
info2soft/active/__init__.py
info2soft/active/test/__init__.py
info2soft/active/test/v20200720/DataChkTest.py
info2soft/active/test/v20200720/Db2Test.py
info2soft/active/test/v20200720/DmTest.py
info2soft/active/test/v20200720/GaussTest.py
info2soft/active/test/v20200720/HeteroTest.py
info2soft/active/test/v20200720/InfomixTest.py
info2soft/active/test/v20200720/LogTest.py
info2soft/active/test/v20200720/MaskTest.py
info2soft/active/test/v20200720/MongoDBTest.py
info2soft/active/test/v20200720/MysqlTest.py
info2soft/active/test/v20200720/NodeTest.py
info2soft/active/test/v20200720/NotificationsTest.py
info2soft/active/test/v20200720/OceanbaseTest.py
info2soft/active/test/v20200720/OracleRuleTest.py
info2soft/active/test/v20200720/PostgresTest.py
info2soft/active/test/v20200720/QianBaseSyncTest.py
info2soft/active/test/v20200720/QianBasexTPTest.py
info2soft/active/test/v20200720/ScriptMaskTest.py
info2soft/active/test/v20200720/SqlserverTest.py
info2soft/active/test/v20200720/SummaryTest.py
info2soft/active/test/v20200720/SyncRulesTest.py
info2soft/active/test/v20200720/TidbTest.py
info2soft/active/test/v20200720/__init__.py
info2soft/active/test/v20220622/DataChkTest.py
i2up_Python_SDK-9.1.3.dist-info/LICENSE
i2up_Python_SDK-9.1.3.dist-info/METADATA
i2up_Python_SDK-9.1.3.dist-info/WHEEL
i2up_Python_SDK-9.1.3.dist-info/top_level.txt
i2up_Python_SDK-9.1.3.dist-info/RECORD
