Metadata-Version: 2.1
Name: i2up_Python_SDK
Version: 9.1.3
Summary: 英方统一数据管理平台python版本SDK
Author: wanghl
Author-email: wanghl@info2soft.com
Classifier: Programming Language :: Python :: 3
Classifier: License :: OSI Approved :: Artistic License
Classifier: Operating System :: OS Independent
Requires-Python: >=3
License-File: LICENSE
Requires-Dist: numpy
Requires-Dist: requests
Requires-Dist: simplejson
Requires-Dist: pytest
Requires-Dist: flake8
Requires-Dist: rsa
Requires-Dist: crypto
Requires-Dist: pycryptodome
Requires-Dist: pyopenssl
